{"pladesantamaria":["Spain"],"pladelpenedesel":["Spain"],"plabennec":["France"],"placanica":["Italy"],"placas":["Brazil"],"placencia":["Belize"],"placentia":["United States"],"placer":["Philippines"],"placercounty":["United States"],"placeresdeloro":["Mexico"],"placerville":["United States"],"placetas":["Cuba"],"placidlakes":["United States"],"placilla":["Chile"],"placitas":["United States"],"plaffeien":["Switzerland"],"plagiari":["Greece"],"plaidt":["Germany"],"plailly":["France"],"plaimpiedgivaudins":["France"],"plaincity":["United States"],"plainview":["United States"],"plainedespapayes":["Mauritius"],"plainedunord":["Haiti"],"plainemagnien":["Mauritius"],"plainehaute":["France"],"plainedge":["United States"],"plainesdesroches":["Mauritius"],"plainfaing":["France"],"plainfeld":["Austria"],"plainfield":["United States"],"plainfieldvillage":["United States"],"plainland":["Australia"],"plains":["United Kingdom","United States"],"plainsborocenter":["United States"],"plaintel":["France"],"plainville":["United States"],"plainwell":["United States"],"plaisance":["France","Haiti"],"plaisancedutouch":["France"],"plaisir":["France"],"plaistow":["United States"],"plakhtiyivka":["Ukraine"],"plan":["Spain"],"plandintrod":["Italy"],"plandeaguaprieta":["Mexico"],"plandearroyos":["Mexico"],"plandeayala":["Mexico"],"plandeayalacampocinco":["Mexico"],"plandechorcha":["Panama"],"plandeiguala":["Mexico"],"plandelashayas":["Mexico"],"plandelrio":["Mexico"],"planguanajuatolasandia":["Mexico"],"plandaupssaintebaume":["France"],"plandecuques":["France"],"planlesouates":["Switzerland"],"planada":["United States"],"planadas":["Colombia"],"planaltina":["Brazil"],"planaltinadoparana":["Brazil"],"planaltino":["Brazil"],"planalto":["Brazil"],"planaltoalegre":["Brazil"],"planaltodaserra":["Brazil"],"planard":["Saint Lucia"],"plancarte":["Mexico"],"plancherbas":["France"],"plancherlesmines":["France"],"plancoet":["France"],"plandiste":["Serbia"],"plandome":["United States"],"plandomeheights":["United States"],"planegg":["Germany"],"planes":["Spain"],"planesdhostolesles":["Spain"],"planetarica":["Colombia"],"planguenoual":["France"],"planken":["Liechtenstein"],"plankenau":["Austria"],"plankinton":["United States"],"plankstadt":["Germany"],"plano":["United States"],"planoles":["Spain"],"planovskoye":["Russia"],"plansdesioels":["Spain"],"plantcity":["United States"],"plantagenet":["Canada"],"plantagenetshire":["Australia"],"plantation":["United States"],"plantationmobilehomepark":["United States"],"plantersville":["United States"],"planura":["Brazil"],"plana":["Czech Republic"],"plananadluznici":["Czech Republic"],"plappeville":["France"],"plaquemine":["United States"],"plaqueminesparish":["United States"],"plaridel":["Philippines"],"plasencia":["Spain"],"plasenciadejalon":["Spain"],"plasenzuela":["Spain"],"plasnica":["Macedonia"],"plast":["Russia"],"plastun":["Russia"],"plastunovskaya":["Russia"],"plasy":["Czech Republic"],"platpays":["Saint Lucia"],"plataci":["Italy"],"platagata":["Philippines"],"platania":["Italy"],"platanillo":["Mexico"],"platanorevma":["Greece"],"plataria":["Greece"],"plate":["Germany"],"plateau":["Saint Lucia"],"plateliai":["Lithuania"],"plateros":["Mexico"],"platina":["Brazil"],"platicevo":["Serbia"],"platnirovskaya":["Russia"],"plato":["Colombia"],"platonesti":["Romania"],"platonovka":["Russia"],"platte":["United States"],"plattecity":["United States"],"plattecounty":["United States"],"plattekill":["United States"],"plattenburg":["Germany"],"platteville":["United States"],"plattling":["Germany"],"plattsburg":["United States"],"plattsburgh":["United States"],"plattsburghwest":["United States"],"plattsmouth":["United States"],"plattsville":["Canada"],"plati":["Italy"],"platonsanchez":["Mexico"],"platy":["Greece"],"plauamsee":["Germany"],"plaudren":["France"],"plaue":["Germany"],"plauen":["Germany"],"plaus":["Italy"],"plauzat":["France"],"plav":["Montenegro"],"plavsk":["Russia"],"plavy":["Czech Republic"],"playaazul":["Mexico"],"playablanca":["Spain"],"playachica":["Mexico"],"playachiquita":["Panama"],"playadechachalacas":["Mexico"],"playadelalibertad":["Mexico"],"playadelasamericas":["Spain"],"playadelcarmen":["Mexico"],"playadelingles":["Spain"],"playafortuna":["United States"],"playagrande":["Guatemala"],"playaleona":["Panama"],"playavicente":["Mexico"],"playas":["Ecuador"],"playasderosarito":["Mexico"],"playasdelrosario":["Mexico"],"playford":["Australia"],"playita":["United States"],"playitacortada":["United States"],"playonchico":["Panama"],"plazadecaisan":["Panama"],"plazahuincul":["Argentina"],"plazanueva":["Mexico"],"planany":["Czech Republic"],"pleak":["United States"],"plean":["United Kingdom"],"pleasantgap":["United States"],"pleasantgarden":["United States"],"pleasantgrove":["United States"],"pleasanthill":["United States"],"pleasanthills":["United States"],"pleasantpoint":["New Zealand"],"pleasantprairie":["United States"],"pleasantridge":["United States"],"pleasantrun":["United States"],"pleasantrunfarm":["United States"],"pleasantvalley":["Jamaica","United States"],"pleasantview":["United States"],"pleasanton":["United States"],"pleasantscounty":["United States"],"pleasantville":["United States"],"pleasureridgepark":["United States"],"pleaux":["France"],"pleasa":["Romania"],"pleasov":["Romania"],"pleidelsheim":["Germany"],"pleiku":["Vietnam"],"pleinefougeres":["France"],"pleinfeld":["Germany"],"pleiskirchen":["Germany"],"pleitas":["Spain"],"plekhanovo":["Russia"],"plenas":["Spain"],"plenita":["Romania"],"plenty":["Australia"],"plentywood":["United States"],"plentzia":["Spain"],"plerguer":["France"],"plesching":["Austria"],"plescop":["France"],"plesetsk":["Russia"],"pleshanovo":["Russia"],"plesio":["Italy"],"pleslintrigavou":["France"],"plesna":["Poland"],"plessa":["Germany"],"plessala":["France"],"plessisville":["Canada"],"plesse":["France"],"plestan":["France"],"plestinlesgreves":["France"],"pleszew":["Poland"],"pleternica":["Croatia"],"plettenberg":["Germany"],"plettenbergbay":["South Africa"],"pleubian":["France"],"pleucadeuc":["France"],"pleudaniel":["France"],"pleudihensurrance":["France"],"pleugriffet":["France"],"pleugueneuc":["France"],"pleumartin":["France"],"pleumeleuc":["France"],"pleumeurbodou":["France"],"pleumeurgautier":["France"],"pleurtuit":["France"],"pleuven":["France"],"pleven":["Bulgaria"],"plevna":["Romania"],"plewiska":["Poland"],"pleyben":["France"],"pleyberchrist":["France"],"pleyne":["Italy"],"pleystein":["Germany"],"plescuta":["Romania"],"plesoiu":["Romania"],"plesoi":["Romania"],"pliego":["Spain"],"pliening":["Germany"],"pliezhausen":["Germany"],"plitvickajezera":["Croatia"],"pljevlja":["Montenegro"],"ploaghe":["Italy"],"plobannaleclesconil":["France"],"plobsheim":["France"],"plochingen":["Germany"],"plodio":["Italy"],"plodovoye":["Ukraine"],"ploemel":["France"],"ploemeur":["France"],"ploeren":["France"],"plogastelsaintgermain":["France"],"plogoff":["France"],"plogonnec":["France"],"ploiesti":["Romania"],"ploiestiori":["Romania"],"plombieres":["Belgium"],"plombiereslesbains":["France"],"plombiereslesdijon":["France"],"plomelin":["France"],"plomeur":["France"],"plomodiern":["France"],"ploneis":["France"],"ploneourlanvern":["France"],"plonevezdufaou":["France"],"plonevezporzay":["France"],"plopana":["Romania"],"plopeni":["Romania"],"plopiislavitesti":["Romania"],"plopis":["Romania"],"plopu":["Romania"],"plopsoru":["Romania"],"plosca":["Romania"],"ploscos":["Romania"],"ploscuteni":["Romania"],"plotnikovo":["Russia"],"plottier":["Argentina"],"plou":["Spain"],"plouagat":["France"],"plouaret":["France"],"plouarzel":["France"],"plouasne":["France"],"plouay":["France"],"ploubalay":["France"],"ploubazlanec":["France"],"ploubezre":["France"],"ploudalmezeau":["France"],"ploudaniel":["France"],"plouescat":["France"],"plouezoch":["France"],"ploufragan":["France"],"plougasnou":["France"],"plougasteldaoulas":["France"],"plougonvelin":["France"],"plougonven":["France"],"plougoulm":["France"],"plougoumelen":["France"],"plougourvest":["France"],"plougrescant":["France"],"plouguenast":["France"],"plouguerneau":["France"],"plouguernevel":["France"],"plouguiel":["France"],"plouguin":["France"],"plouha":["France"],"plouharnel":["France"],"plouhinec":["France"],"plouider":["France"],"plouigneau":["France"],"plouisy":["France"],"ploumagoar":["France"],"ploumilliau":["France"],"ploumoguer":["France"],"plouneourmenez":["France"],"plouneourtrez":["France"],"plouneventer":["France"],"plounevezlochrist":["France"],"plounevezmoedec":["France"],"plounevezquintin":["France"],"plounevezel":["France"],"plouray":["France"],"plourinlesmorlaix":["France"],"plourivo":["France"],"plouvien":["France"],"plouvorn":["France"],"plouzane":["France"],"plouzevede":["France"],"plouedern":["France"],"plouenan":["France"],"plouezec":["France"],"plouecdutrieux":["France"],"plouersurrance":["France"],"plovdiv":["Bulgaria"],"plover":["United States"],"plowden":["Jamaica"],"plozevet":["France"],"ploerdut":["France"],"ploermel":["France"],"ploezal":["France"],"plostina":["Romania"],"pluduno":["France"],"plugari":["Romania"],"plugova":["Romania"],"pluguffan":["France"],"pluherlin":["France"],"plum":["United States"],"plumcreek":["United States"],"plumgrove":["United States"],"plumahidalgo":["Mexico"],"plumascounty":["United States"],"plumaslake":["United States"],"plumaugat":["France"],"plumbon":["Indonesia"],"plumelec":["France"],"plumelin":["France"],"plumergat":["France"],"plumieux":["France"],"plumlov":["Czech Republic"],"plummer":["United States"],"plumpton":["Australia"],"plumptongreen":["United Kingdom"],"plumsteadville":["United States"],"plumtree":["Zimbabwe"],"plumeliau":["France"],"pluneret":["France"],"plunge":["Lithuania"],"plurien":["France"],"plut":["Saint Lucia"],"plutarcoeliascalleslaygriega":["Mexico"],"plutonita":["Romania"],"pluvigner":["France"],"pluwig":["Germany"],"pluzunet":["France"],"pluzine":["Montenegro"],"plyeshchanitsy":["Belarus"],"plymouth":["United Kingdom","United States"],"plymouthcounty":["United States"],"plymouthmeeting":["United States"],"plympton":["Australia","United Kingdom","United States"],"plymptonpark":["Australia"],"plymstock":["United Kingdom"],"plyussa":["Russia"],"placidodecastro":["Brazil"],"plakadilesi":["Greece"],"planice":["Czech Republic"],"platanos":["Greece"],"planterwald":["Germany"],"plechatel":["France"],"pledran":["France"],"pledeliac":["France"],"pleguien":["France"],"plehedel":["France"],"plelanlegrand":["France"],"plelanlepetit":["France"],"plelo":["France"],"plemet":["France"],"plemy":["France"],"pleneufvalandre":["France"],"pleneejugon":["France"],"plerin":["France"],"ples":["Russia"],"plon":["Germany"],"plotzkau":["Germany"],"plotzky":["Germany"],"plossberg":["Germany"],"pluderhausen":["Germany"],"plataresti":["Romania"],"plavalari":["Romania"],"ploeucsurlie":["France"],"plavinas":["Latvia"],"plawno":["Poland"],"plaza":["Poland"],"plock":["Poland"],"ploniawybramura":["Poland"],"ploty":["Poland"],"plonsk":["Poland"],"pluznica":["Poland"]}