{"ava":["Iran","United States"],"avadi":["India"],"availleslimouzine":["France"],"avaj":["Iran"],"avajiq":["Iran"],"avallon":["France"],"avalon":["United States"],"avanca":["Portugal"],"avane":["Italy"],"avanhandava":["Brazil"],"avanigadda":["India"],"avanneaveney":["France"],"avanoor":["India"],"avanos":["Turkey"],"avanton":["France"],"avarzaman":["Iran"],"avare":["Brazil"],"avai":["Brazil"],"avcilar":["Turkey"],"avdiyivka":["Ukraine"],"avdon":["Russia"],"avemaria":["Panama"],"avegno":["Italy"],"aveh":["Iran"],"aveinte":["Spain"],"aveirasdebaixo":["Portugal"],"aveirasdecima":["Portugal"],"aveiro":["Brazil","Portugal"],"aveize":["France"],"aveizieux":["France"],"aveleda":["Portugal"],"avelengo":["Italy"],"aveley":["Australia","United Kingdom"],"avelgem":["Belgium"],"avelin":["France"],"avelinolopes":["Brazil"],"avelinopolis":["Brazil"],"avella":["Italy"],"avellaneda":["Argentina","Spain"],"avellanesisantalinyales":["Spain"],"avellanosademuno":["Spain"],"avellino":["Italy"],"aveloso":["Portugal"],"avelasdaribeira":["Portugal"],"avenal":["United States"],"avenches":["Switzerland"],"avenel":["Australia","United States"],"avenellheights":["Australia"],"avenhorn":["Netherlands"],"avening":["United Kingdom"],"avensan":["France"],"aventura":["United States"],"avenuebandc":["United States"],"averomar":["Portugal"],"averara":["Italy"],"averillpark":["United States"],"avermes":["France"],"aversa":["Italy"],"averycounty":["United States"],"averycreek":["United States"],"averoy":["Norway"],"aves":["Portugal"],"avesnelles":["France"],"avesneslecomte":["France"],"avesneslesec":["France"],"avesneslesaubert":["France"],"avessac":["France"],"avesta":["Sweden"],"avetrana":["Italy"],"avezzano":["Italy"],"avgorou":["Cyprus"],"aviano":["Italy"],"avianocastello":["Italy"],"aviatico":["Italy"],"aviatorske":["Ukraine"],"aviemore":["United Kingdom"],"avigliana":["Italy"],"avigliano":["Italy"],"aviglianoumbro":["Italy"],"avignon":["France"],"avignonetlauragais":["France"],"avila":["Spain"],"avilabeach":["United States"],"avilla":["United States"],"avillysaintleonard":["France"],"aviles":["Spain"],"avinashi":["India"],"avine":["Turkey"],"avintes":["Portugal"],"avinyonetdepuigventos":["Spain"],"avinyonetdelpenedes":["Spain"],"avinyo":["Spain"],"avio":["Italy"],"avion":["Spain"],"aviron":["France"],"avis":["Portugal","United States"],"avise":["Italy"],"aviski":["Turkey"],"aviston":["United States"],"avize":["France"],"avia":["Spain"],"aviaterai":["Argentina"],"avlum":["Denmark"],"avlonas":["Greece"],"avoca":["Australia","United States"],"avocabeach":["Australia"],"avocadoheights":["United States"],"avoine":["France"],"avola":["Italy"],"avolasca":["Italy"],"avon":["France","United States"],"avoncenter":["United States"],"avonlake":["United States"],"avonpark":["United States"],"avonbythesea":["United States"],"avondale":["Australia","United States"],"avondaleestates":["United States"],"avondaleheights":["Australia"],"avonia":["United States"],"avord":["France"],"avoyellesparish":["United States"],"avravalley":["United States"],"avramiancu":["Romania"],"avranches":["France"],"avratin":["Ukraine"],"avrechy":["France"],"avrig":["Romania"],"avrille":["France"],"avrysurmatran":["Switzerland"],"avrameni":["Romania"],"avramesti":["Romania"],"avsallar":["Turkey"],"avshar":["Armenia"],"avsyunino":["Russia"],"avtopoligon":["Russia"],"avtovo":["Russia"],"avtury":["Russia"],"avvocata":["Italy"],"aveze":["France"],"avsar":["Azerbaijan"],"avanuorri":["Norway"],"avato":["Greece"]}