{"vi":["Sweden"],"vialippia":["Italy"],"viacampylitera":["Spain"],"viadana":["Italy"],"viadanica":["Italy"],"viadutos":["Brazil"],"viagrande":["Italy"],"viale":["Argentina","Italy"],"vialfre":["Italy"],"vialonga":["Portugal"],"viamonte":["Argentina"],"viamao":["Brazil"],"vian":["United States"],"viana":["Brazil","Spain"],"vianadecega":["Spain"],"vianadeduero":["Spain"],"vianadejadraque":["Spain"],"vianadoalentejo":["Portugal"],"vianadobolo":["Spain"],"vianadocastelo":["Portugal"],"viandardelavera":["Spain"],"vianden":["Luxembourg"],"vianen":["Netherlands"],"vianne":["France"],"viano":["Italy"],"vianos":["Spain"],"viani":["Colombia"],"vianopolis":["Brazil"],"viareggio":["Italy"],"viarigi":["Italy"],"viarmes":["France"],"vias":["France"],"viator":["Spain"],"vibble":["Sweden"],"vibovalentia":["Italy"],"vibonati":["Italy"],"viborg":["Denmark"],"viborgkommune":["Denmark"],"viborillas":["Mexico"],"vibraye":["France"],"viby":["Denmark"],"vic":["Spain"],"vicenbigorre":["France"],"vicfezensac":["France"],"viclagardiole":["France"],"viclecomte":["France"],"vicsuraisne":["France"],"vicsurcere":["France"],"vicsurseille":["France"],"vicalvi":["Italy"],"vicam":["Mexico"],"vicarello":["Italy"],"vicari":["Italy"],"vicaria":["Italy"],"vicchio":["Italy"],"vice":["Peru"],"vicea":["Romania"],"vicedoo":["Spain"],"vicentecamalote":["Mexico"],"vicentedutra":["Brazil"],"vicenteguerrero":["Mexico"],"vicenteguerrerosanjavier":["Mexico"],"vicenteherrera":["Mexico"],"vicentenoble":["Dominican Republic"],"vicentina":["Brazil"],"vicentinopolis":["Brazil"],"vicenza":["Italy"],"vichadero":["Uruguay"],"vichten":["Luxembourg"],"vichuga":["Russia"],"vichugskiyrayon":["Russia"],"vichuquen":["Chile"],"vichy":["France"],"viciomaggio":["Italy"],"vicien":["Spain"],"vicksburg":["United States"],"vicocanavese":["Italy"],"vicodelgargano":["Italy"],"vicoequense":["Italy"],"viconellazio":["Italy"],"vicofertile":["Italy"],"vicoforte":["Italy"],"vicoli":["Italy"],"vicolungo":["Italy"],"vicomoscano":["Italy"],"vicopisano":["Italy"],"vicovaro":["Italy"],"vicovudejos":["Romania"],"vicovudesus":["Romania"],"vicq":["France"],"vicqsurbreuilh":["France"],"vicques":["Switzerland"],"victor":["United States"],"victorgraeff":["Brazil"],"victorharbor":["Australia"],"victorvladdelamarina":["Romania"],"victoria":["Argentina","Canada","Chile","Colombia","El Salvador","Grenada","Honduras","Malta","Mexico","Philippines","Romania","Saint Lucia","Seychelles","United Kingdom","United States"],"victoriacounty":["United States"],"victoriadaly":["Australia"],"victoriadeacentejola":["Spain"],"victoriadecortazar":["Mexico"],"victoriadedurango":["Mexico"],"victoriafalls":["Zimbabwe"],"victoriala":["Spain"],"victoriapark":["Australia"],"victoriaplains":["Australia"],"victoriapoint":["Australia"],"victoriatown":["Jamaica"],"victorias":["Philippines"],"victoriaville":["Canada"],"victorica":["Argentina"],"victorville":["United States"],"victorygardens":["United States"],"victorylakes":["United States"],"vicuna":["Chile"],"vicunamackenna":["Argentina"],"vicalvaro":["Spain"],"vicencia":["Brazil"],"viddeburebala":["Spain"],"viddeojedala":["Spain"],"vidybarriosla":["Spain"],"vidamejori":["Mexico"],"vidais":["Portugal"],"vidalramos":["Brazil"],"vidalengo":["Italy"],"vidalia":["United States"],"vidardo":["Italy"],"vidauban":["France"],"vidayanes":["Spain"],"viddalba":["Italy"],"vide":["Portugal"],"videbouteille":["Saint Lucia"],"videentrevinhas":["Portugal"],"videbaek":["Denmark"],"videira":["Brazil"],"videle":["Romania"],"videm":["Slovenia"],"vidempriptuju":["Slovenia"],"videmala":["Spain"],"videmonte":["Portugal"],"vidigueira":["Portugal"],"vidigulfo":["Italy"],"vidim":["Russia"],"vidin":["Bulgaria"],"vidisha":["India"],"vidnava":["Czech Republic"],"vidnoye":["Russia"],"vidor":["Italy","United States"],"vidovci":["Croatia"],"vidovec":["Croatia"],"vidosi":["Bosnia and Herzegovina"],"vidra":["Spain"],"vidracco":["Italy"],"vidrasau":["Romania"],"vidreres":["Spain"],"vidyayevo":["Russia"],"vidzy":["Belarus"],"vidangozbidankoze":["Spain"],"vidce":["Czech Republic"],"viechtach":["Germany"],"viechtwang":["Austria"],"viedma":["Argentina"],"viehhausen":["Austria"],"viehhofen":["Austria"],"viehofen":["Austria"],"vieillechapelle":["France"],"vieillebrioude":["France"],"vieilletoulouse":["France"],"vieilleeglise":["France"],"vieillevigne":["France"],"vieiradeleiria":["Portugal"],"vieiradominho":["Portugal"],"vieiras":["Brazil"],"vieiropolis":["Brazil"],"viejodaanbanua":["Philippines"],"vieksniai":["Lithuania"],"vielhaemijaran":["Spain"],"viellesaintgirons":["France"],"vielmursuragout":["France"],"vielsalm":["Belgium"],"vienenburg":["Germany"],"vienna":["Austria","United States"],"viennabend":["United States"],"viennay":["France"],"vienne":["France"],"vienneenval":["France"],"vientiane":["Laos"],"vientofrio":["Panama"],"vieques":["United States"],"viequesmunicipality":["United States"],"vieraeast":["United States"],"vierawest":["United States"],"viereck":["Germany"],"vierethtrunstadt":["Germany"],"vierkirchen":["Germany"],"vierlas":["Spain"],"viernau":["Germany"],"viernheim":["Germany"],"vierpolders":["Netherlands"],"viersen":["Germany"],"vieru":["Romania"],"vierzon":["France"],"viersani":["Romania"],"viesca":["Mexico"],"viesly":["France"],"vieste":["Italy"],"viesite":["Latvia"],"vietridipotenza":["Italy"],"vietrisulmare":["Italy"],"vieuxfort":["Saint Lucia"],"vieuxfortlaboriehighway":["Saint Lucia"],"vieuxberquin":["France"],"vieuxboucaulesbains":["France"],"vieuxcharmont":["France"],"vieuxconde":["France"],"vieuxthann":["France"],"vievis":["Lithuania"],"viewparkwindsorhills":["United States"],"viewbank":["Australia"],"viewpark":["United Kingdom"],"vif":["France"],"viforoasa":["Romania"],"viforata":["Romania"],"viga":["Philippines"],"vigan":["Philippines"],"viganella":["Italy"],"viganello":["Switzerland"],"viganosanmartino":["Italy"],"vigano":["Italy"],"vigaranomainarda":["Italy"],"vigaranopieve":["Italy"],"vigardolo":["Italy"],"vigasio":["Italy"],"vigatto":["Italy"],"vigaun":["Austria"],"vige":["Saint Lucia"],"vigeland":["Norway"],"vigeois":["France"],"vigevano":["Italy"],"viggianello":["Italy"],"viggiano":["Italy"],"viggiu":["Italy"],"vighignolo":["Italy"],"vighizzolo":["Italy"],"vighizzolodeste":["Italy"],"vigia":["Brazil"],"vigie":["Saint Lucia"],"viglianobiellese":["Italy"],"viglianodasti":["Italy"],"viglianobettolino":["Italy"],"vigliatore2":["Italy"],"vignacastrisi":["Italy"],"vignacourt":["France"],"vignalemonferrato":["Italy"],"vignaleriotorto":["Italy"],"vignanello":["Italy"],"vignate":["Italy"],"vigneullesleshattonchatel":["France"],"vigneuxdebretagne":["France"],"vigneuxsurseine":["France"],"vignoc":["France"],"vignola":["Italy"],"vignoleborbera":["Italy"],"vignoleolmi":["Italy"],"vignolo":["Italy"],"vignone":["Italy"],"vignot":["France"],"vignouxsurbarangeon":["France"],"vigny":["France"],"vigo":["Philippines","Spain"],"vigocounty":["United States"],"vigodicadore":["Italy"],"vigodifassa":["Italy"],"vigoditon":["Italy"],"vigodarzere":["Italy"],"vigolo":["Italy"],"vigolovattaro":["Italy"],"vigolzone":["Italy"],"vigone":["Italy"],"vigonovo":["Italy"],"vigonovofontanafredda":["Italy"],"vigonza":["Italy"],"vigonzone":["Italy"],"vigrestad":["Norway"],"viguera":["Spain"],"viguzzolo":["Italy"],"vigui":["Panama"],"vigy":["France"],"vigiadelfuerte":["Colombia"],"vihanti":["Finland"],"vihari":["Pakistan"],"vihiers":["France"],"vihti":["Finland"],"viiala":["Finland"],"viile":["Romania"],"viileapei":["Romania"],"viilesatumare":["Romania"],"viiletecii":["Romania"],"viilor":["Romania"],"viimsi":["Estonia"],"viimsivald":["Estonia"],"viiratsi":["Estonia"],"viitasaari":["Finland"],"viisoara":["Romania"],"vijapur":["India"],"vijayapura":["India"],"vijayapuri":["India"],"vijayawada":["India"],"vijaydurg":["India"],"vijes":["Colombia"],"vijfhuizen":["Netherlands"],"vijlen":["Netherlands"],"vik":["Norway"],"vikarabad":["India"],"vikarbyn":["Sweden"],"vikasnagar":["India"],"viken":["Sweden"],"vikersund":["Norway"],"vikesa":["Norway"],"vikevag":["Norway"],"vikhorevka":["Russia"],"vikhroli":["India"],"vikindu":["Tanzania"],"viking":["Canada"],"vikingstad":["Sweden"],"vikna":["Norway"],"vikravandi":["India"],"viktorsberg":["Austria"],"viktring":["Austria"],"viktringervorstadt":["Austria"],"vikulovo":["Russia"],"vikyrovice":["Czech Republic"],"vilabeladasantissimatrindade":["Brazil"],"vilaboa":["Spain"],"vilaboadomondego":["Portugal"],"vilacha":["Portugal"],"vilachadeourique":["Portugal"],"vilacortesdaserra":["Portugal"],"vilacortesdomondego":["Portugal"],"vilacova":["Portugal"],"vilacovaacoelheira":["Portugal"],"viladecruces":["Spain"],"viladerei":["Portugal"],"viladobispo":["Portugal"],"viladoconde":["Portugal"],"viladomaio":["Cape Verde"],"viladoporto":["Portugal"],"viladotouro":["Portugal"],"vilafernando":["Portugal"],"vilaflor":["Spain"],"vilaflores":["Brazil"],"vilafrancadaserra":["Portugal"],"vilafrancadasnaves":["Portugal"],"vilafrancadexira":["Portugal"],"vilafrancadocampo":["Portugal"],"vilafrancadodeao":["Portugal"],"vilafrancadorosario":["Portugal"],"vilafrescainha":["Portugal"],"vilagarcia":["Portugal"],"vilalangaro":["Brazil"],"vilamaria":["Brazil"],"vilamea":["Portugal"],"vilanovadabarquinha":["Portugal"],"vilanovadarainha":["Portugal"],"vilanovadatelha":["Portugal"],"vilanovadecacela":["Portugal"],"vilanovadefamalicao":["Portugal"],"vilanovadefozcoa":["Portugal"],"vilanovadegaia":["Portugal"],"vilanovademilfontes":["Portugal"],"vilanovadepaiva":["Portugal"],"vilanovadepoiares":["Portugal"],"vilanovadesaopedro":["Portugal"],"vilanovadetazem":["Portugal"],"vilanovadopiaui":["Brazil"],"vilanovadosul":["Brazil"],"vilanovadosmartirios":["Brazil"],"vilapavao":["Brazil"],"vilapoucadeaguiar":["Portugal"],"vilapropicio":["Brazil"],"vilareal":["Spain"],"vilarealdesantoantonio":["Portugal"],"vilarica":["Brazil"],"vilaruiva":["Portugal"],"vilaseca":["Spain"],"vilasoeirodochao":["Portugal"],"vilavalerio":["Brazil"],"vilavelha":["Brazil"],"vilavelhaderodao":["Portugal"],"vilaverde":["Portugal"],"vilaverdedosfrancos":["Portugal"],"vilavicosa":["Portugal"],"vilarodona":["Spain"],"vilasacra":["Spain"],"vilasana":["Spain"],"vilabella":["Spain"],"vilabertran":["Spain"],"vilablareix":["Spain"],"vilada":["Spain"],"viladamat":["Spain"],"viladasens":["Spain"],"viladecans":["Spain"],"viladecavalls":["Spain"],"vilademuls":["Spain"],"viladrau":["Spain"],"vilafames":["Spain"],"vilafant":["Spain"],"vilafrancadebonany":["Spain"],"vilafrancadelpenedes":["Spain"],"vilagarciadearousa":["Spain"],"vilagrassa":["Spain"],"vilajuiga":["Spain"],"vilalba":["Spain"],"vilalbadelsarcs":["Spain"],"vilalbasasserra":["Spain"],"vilaller":["Spain"],"vilallongadeter":["Spain"],"vilallongadelcamp":["Spain"],"vilallongadelsmonts":["France"],"vilamacolum":["Spain"],"vilamalla":["Spain"],"vilamaniscle":["Spain"],"vilamartindevaldeorras":["Spain"],"vilamarxant":["Spain"],"vilamarin":["Spain"],"vilamoura":["Portugal"],"vilamos":["Spain"],"vilanant":["Spain"],"vilanovadalcolea":["Spain"],"vilanovadearousa":["Spain"],"vilanovadebellpuig":["Spain"],"vilanovadelabarca":["Spain"],"vilanovadelaguda":["Spain"],"vilanovademeia":["Spain"],"vilanovadeprades":["Spain"],"vilanovadesau":["Spain"],"vilanovadesegria":["Spain"],"vilanovadelcami":["Spain"],"vilanovadelvalles":["Spain"],"vilanovadescornalbou":["Spain"],"vilanovailageltru":["Spain"],"vilaplana":["Spain"],"vilar":["Portugal"],"vilardeamargo":["Portugal"],"vilardeandorinho":["Portugal"],"vilardebarrio":["Spain"],"vilardecanes":["Spain"],"vilardefigos":["Portugal"],"vilardesantos":["Spain"],"vilardoparaiso":["Portugal"],"vilarformoso":["Portugal"],"vilarmaior":["Spain"],"vilartorpim":["Portugal"],"vilardevos":["Spain"],"vilares":["Portugal"],"vilarinho":["Portugal"],"vilarinodeconso":["Spain"],"vilascounty":["United States"],"vilasantar":["Spain"],"vilassardedalt":["Spain"],"vilassardemar":["Spain"],"vilattikulam":["India"],"vilavellala":["Spain"],"vilaverd":["Spain"],"vilaxoan":["Spain"],"vilaca":["Portugal"],"vilaur":["Spain"],"vilches":["Spain"],"vilcun":["Chile"],"vildbjerg":["Denmark"],"vileparle":["India"],"vilela":["Portugal"],"vilellaaltala":["Spain"],"vilellabaixala":["Spain"],"vilenka":["Russia"],"vilena":["Spain"],"vilgertshofen":["Germany"],"vilhelmina":["Sweden"],"vilhena":["Brazil"],"viligili":["Maldives"],"vilino":["Ukraine"],"viljakkala":["Finland"],"viljandi":["Estonia"],"viljandivald":["Estonia"],"viljevo":["Croatia"],"viljoenskroon":["South Africa"],"vilkaviskis":["Lithuania"],"vilkaviskisdistrictmunicipality":["Lithuania"],"vilkija":["Lithuania"],"vilkpede":["Lithuania"],"villalbese":["Italy"],"villa":["Italy"],"villaadriana":["Italy"],"villaaglipay":["Philippines"],"villaalbertoandresalvaradoaramburo":["Mexico"],"villaaldama":["Mexico"],"villaalegre":["Chile"],"villaalemana":["Chile"],"villaallende":["Argentina"],"villaalta":["Mexico"],"villaaltagracia":["Dominican Republic"],"villaascasubi":["Argentina"],"villaatamisqui":["Argentina"],"villaavilacamacho":["Mexico"],"villaazueta":["Mexico"],"villabartolomea":["Italy"],"villabasilica":["Italy"],"villabasilionievas":["Argentina"],"villaberna":["Argentina"],"villaberthet":["Argentina"],"villabiscossi":["Italy"],"villabisono":["Dominican Republic"],"villabruzual":["Venezuela"],"villabustos":["Argentina"],"villacaldari":["Italy"],"villacanales":["Guatemala"],"villacarcina":["Italy"],"villacarlospaz":["Argentina"],"villacarmen":["Panama"],"villacaro":["Colombia"],"villacastelli":["Italy"],"villacanas":["Spain"],"villaceccolini":["Italy"],"villaceliera":["Italy"],"villachalcatongodehidalgo":["Mexico"],"villaciambra":["Italy"],"villacollemandina":["Italy"],"villacomaltitlan":["Mexico"],"villaconcepciondeltio":["Argentina"],"villaconstitucion":["Argentina","Uruguay"],"villaconsuelo":["Dominican Republic"],"villacorona":["Mexico"],"villacortese":["Italy"],"villacorzo":["Mexico"],"villacuauhtemoc":["Mexico"],"villacurabrochero":["Argentina"],"villadadda":["Italy"],"villadagri":["Italy"],"villadalme":["Italy"],"villadasolo":["Italy"],"villadogna":["Italy"],"villadoneta":["Italy"],"villadealmoloyadejuarez":["Mexico"],"villadecos":["Mexico"],"villadecostarica":["Mexico"],"villadecura":["Venezuela"],"villadedonfadriquela":["Spain"],"villadeelcarmentequexquitla":["Mexico"],"villadeetla":["Mexico"],"villadeguadalupe":["Mexico"],"villadelasflores":["Mexico"],"villadeleyva":["Colombia"],"villadelosninos":["Mexico"],"villademazo":["Spain"],"villaderamos":["Mexico"],"villadereyes":["Mexico"],"villadesanantonio":["Honduras"],"villadesandiegodeubate":["Colombia"],"villadesanfrancisco":["Honduras"],"villadesoto":["Argentina"],"villadetamazulapamdelprogreso":["Mexico"],"villadetututepecdemelchorocampo":["Mexico"],"villadevallecas":["Spain"],"villadeves":["Spain"],"villadezaachila":["Mexico"],"villadelbosco":["Italy"],"villadelcampo":["Mexico","Spain"],"villadelcarbon":["Mexico"],"villadelcarmen":["Uruguay"],"villadelcerro":["Uruguay"],"villadelconte":["Italy"],"villadeldique":["Argentina"],"villadelprado":["Spain"],"villadelprado2daseccion":["Mexico"],"villadelrey":["Spain"],"villadelrosario":["Argentina","Colombia"],"villadelrio":["Spain"],"villadeltotoral":["Argentina"],"villadibriano":["Italy"],"villadichiavenna":["Italy"],"villadiserio":["Italy"],"villadolores":["Argentina"],"villadiazordaz":["Mexico"],"villaelcarmen":["Nicaragua"],"villaelisa":["Argentina","Dominican Republic","Paraguay"],"villaemilianozapata":["Mexico"],"villaemiliocarranza":["Mexico"],"villaescolar":["Argentina"],"villaespanola":["Uruguay"],"villaestense":["Italy"],"villafaraldi":["Italy"],"villaflorida":["Paraguay"],"villafontana":["Italy"],"villafornace":["Italy"],"villafrancisca":["Dominican Republic"],"villagarcia":["Mexico","Uruguay"],"villageneralbelgrano":["Argentina"],"villageneralguemes":["Argentina"],"villageneralmitre":["Argentina"],"villageneralroca":["Argentina"],"villagiardino":["Argentina"],"villagonzalez":["Dominican Republic"],"villagonzalezortega":["Mexico"],"villagregoriogarcia":["Mexico"],"villagrove":["United States"],"villaguardia":["Italy"],"villaguerrero":["Mexico"],"villaguerreromunicipality":["Mexico"],"villahayes":["Paraguay"],"villahermosa":["Colombia","Mexico","Philippines","Spain"],"villahermosalaspozas":["Mexico"],"villahernandarias":["Argentina"],"villahidalgo":["Mexico"],"villahidalgoelcubo":["Mexico"],"villahills":["United States"],"villahuidobro":["Argentina"],"villaindependencia":["Mexico"],"villainsurgenteselcalabazal":["Mexico"],"villaisabela":["Dominican Republic"],"villaisla":["Philippines"],"villajaragua":["Dominican Republic"],"villajimenez":["Mexico"],"villajuarez":["Mexico"],"villalaangostura":["Argentina"],"villalaventa":["Mexico"],"villalagarina":["Italy"],"villalasesperanzas":["Mexico"],"villalasflores":["Mexico"],"villalasrosas":["Argentina"],"villalatina":["Italy"],"villalempa":["Italy"],"villalicenciadojesusterancalvillito":["Mexico"],"villaliterno":["Italy"],"villalourdes":["Panama"],"villalugano":["Argentina"],"villaluvianos":["Mexico"],"villalazarocardenas":["Mexico"],"villamadero":["Mexico"],"villamagna":["Italy"],"villamainero":["Mexico"],"villamantero":["Argentina"],"villamarianomatamoros":["Mexico"],"villamaria":["Colombia"],"villamariagrande":["Argentina"],"villamercedes":["Argentina"],"villaminozzo":["Italy"],"villamontemorelos":["Mexico"],"villamorelos":["Mexico"],"villamugueta":["Argentina"],"villamusone":["Italy"],"villamunoz":["Uruguay"],"villanicolasbravo":["Mexico"],"villanueva":["Colombia","Honduras","Mexico","Philippines"],"villaocampo":["Argentina","Mexico"],"villaojodeagua":["Argentina"],"villaopicina":["Italy"],"villaortuzar":["Argentina"],"villaparanacito":["Argentina"],"villapark":["Netherlands"],"villapauladesarmiento":["Argentina"],"villapedergnano":["Italy"],"villapesqueira":["Mexico"],"villapigna":["Italy"],"villapoma":["Italy"],"villapotenza":["Italy"],"villaprogreso":["Mexico"],"villapurificacion":["Mexico"],"villaraspa":["Italy"],"villaraverio":["Italy"],"villareduccion":["Argentina"],"villaregina":["Argentina"],"villarendena":["Italy"],"villarica":["Colombia","Peru","United States"],"villaridge":["United States"],"villariva":["Dominican Republic"],"villarosa":["Italy","Philippines"],"villarosario":["Panama"],"villarotaria":["Mexico"],"villarumipal":["Argentina"],"villasanfilippo":["Italy"],"villasangiovanni":["Italy"],"villasangiovanniintuscia":["Italy"],"villasangiuseppe":["Italy"],"villasanpietro":["Italy"],"villasansecondo":["Italy"],"villasandino":["Spain"],"villasantangelo":["Italy"],"villasantantonio":["Italy"],"villasantalucia":["Italy"],"villasantaluciadegliabruzzi":["Italy"],"villasantamaria":["Italy"],"villasantarita":["Argentina"],"villasantiago":["Mexico"],"villasantina":["Italy"],"villasantostefano":["Italy"],"villasara":["Uruguay"],"villasoladevega":["Mexico"],"villasoriano":["Uruguay"],"villataleadecastro":["Mexico"],"villatapia":["Dominican Republic"],"villatecolutilla":["Mexico"],"villatejupamdelaunion":["Mexico"],"villatrinidad":["Argentina"],"villatulumba":["Argentina"],"villatupacamaru":["Peru"],"villaunida":["Panama"],"villaunion":["Mexico"],"villaurbidelrey":["Mexico"],"villaurquiza":["Argentina"],"villavaleria":["Argentina"],"villaverde":["Philippines","Spain"],"villaverucchio":["Italy"],"villavicenteguerrero":["Mexico"],"villavicentina":["Italy"],"villavictoria":["Mexico"],"villavasquez":["Dominican Republic"],"villayapacani":["Bolivia"],"villazaragoza":["Mexico"],"villazempoala":["Mexico"],"villaangela":["Argentina"],"villaagnedo":["Italy"],"villaborgo":["Italy"],"villanabian":["Italy"],"villaba":["Philippines"],"villabaruzdecampos":["Spain"],"villabassa":["Italy"],"villabastadevaldavia":["Spain"],"villabate":["Italy"],"villablanca":["Spain"],"villablino":["Spain"],"villabona":["Spain"],"villabraz":["Spain"],"villabrunaumin":["Italy"],"villabragima":["Spain"],"villabrazaro":["Spain"],"villabuenadealavaeskuernaga":["Spain"],"villabuenadelpuente":["Spain"],"villabanez":["Spain"],"villabe":["France"],"villacarralon":["Spain"],"villacarriedo":["Spain"],"villacarrillo":["Spain"],"villacastin":["Spain"],"villach":["Austria"],"villachinnerestadt":["Austria"],"villachlanddistrict":["Austria"],"villachervorstadt":["Austria"],"villachiara":["Italy"],"villachuato":["Mexico"],"villaciddecampos":["Spain"],"villacidaler":["Spain"],"villacidro":["Italy"],"villaciervos":["Spain"],"villaco":["Spain"],"villaconancio":["Spain"],"villaconejos":["Spain"],"villaconejosdetrabaque":["Spain"],"villada":["Spain"],"villadangosdelparamo":["Spain"],"villadeati":["Italy"],"villadecanes":["Spain"],"villademordelavega":["Spain"],"villadepera":["Spain"],"villadiego":["Spain"],"villadose":["Italy"],"villadossola":["Italy"],"villadoz":["Spain"],"villaelesdevaldavia":["Spain"],"villaescusa":["Spain"],"villaescusadeharo":["Spain"],"villaescusaderoa":["Spain"],"villaescusalasombria":["Spain"],"villaespasa":["Spain"],"villafalletto":["Italy"],"villafames":["Spain"],"villafeliche":["Spain"],"villaferruena":["Spain"],"villaflor":["Spain"],"villaflores":["Mexico","Spain"],"villafradesdecampos":["Spain"],"villafranca":["Italy","Spain"],"villafrancadasti":["Italy"],"villafrancadecordoba":["Spain"],"villafrancadeduero":["Spain"],"villafrancadeebro":["Spain"],"villafrancadelasierra":["Spain"],"villafrancadelosbarros":["Spain"],"villafrancadeloscaballeros":["Spain"],"villafrancadelbierzo":["Spain"],"villafrancadelcampo":["Spain"],"villafrancadelcid":["Spain"],"villafrancadelcidvilafranca":["Spain"],"villafrancadiverona":["Italy"],"villafrancainlunigiana":["Italy"],"villafrancamontesdeoca":["Spain"],"villafrancapadovana":["Italy"],"villafrancapiemonte":["Italy"],"villafrancasicula":["Italy"],"villafrancatirrena":["Italy"],"villafrati":["Italy"],"villafrechos":["Spain"],"villafruela":["Spain"],"villafuerte":["Spain"],"villafufre":["Spain"],"villafafila":["Spain"],"villaga":["Italy"],"villagalijo":["Spain"],"villaganzerla":["Italy"],"villagarciadecampos":["Spain"],"villagarciadelatorre":["Spain"],"villagarciadelllano":["Spain"],"villagarzon":["Colombia"],"villagaton":["Spain"],"village":["Saint Lucia"],"villagegreen":["United States"],"villagegreengreenridge":["United States"],"villageofalamrah":["Yemen"],"villageofcamptonhills":["United States"],"villageofoakcreekbigpark":["United States"],"villageofthebranch":["United States"],"villagepark":["United States"],"villagesaintgeorge":["United States"],"villageshires":["United States"],"villageneuf":["France"],"villagepetitebourgh":["Saint Lucia"],"villageriz":["Spain"],"villagesoforiole":["United States"],"villaggiodelpinoleginestre":["Italy"],"villaggiodelsole":["Italy"],"villaggiomontegrappa":["Italy"],"villaggioresidenziale":["Italy"],"villagonzalo":["Spain"],"villagonzalodetormes":["Spain"],"villagonzalopedernales":["Spain"],"villagrande":["Italy"],"villagrandestrisaili":["Italy"],"villagran":["Mexico"],"villaguattera":["Italy"],"villaguay":["Argentina"],"villagomez":["Colombia"],"villagomezlanueva":["Spain"],"villaharta":["Spain"],"villahermosadelcampo":["Spain"],"villahermosadelrio":["Spain"],"villahermosayaluma":["Mexico"],"villaherreros":["Spain"],"villahoz":["Spain"],"villahan":["Spain"],"villaineslajuhel":["France"],"villairamerique":["Italy"],"villajoyosa":["Spain"],"villajoyosavilajoiosala":["Spain"],"villalaco":["Spain"],"villalago":["Italy"],"villalardeloscomuneros":["Spain"],"villalazan":["Spain"],"villalba":["Italy","United States"],"villalbadeduero":["Spain"],"villalbadeguardo":["Spain"],"villalbadelalampreana":["Spain"],"villalbadelaloma":["Spain"],"villalbadelasierra":["Spain"],"villalbadelosalcores":["Spain"],"villalbadelosbarros":["Spain"],"villalbadelosllanos":["Spain"],"villalbadeperejil":["Spain"],"villalbaderioja":["Spain"],"villalbadelalcor":["Spain"],"villalbadelrey":["Spain"],"villalbamunicipio":["United States"],"villalbarba":["Spain"],"villalbilla":["Spain"],"villalbilladeburgos":["Spain"],"villalbilladegumiel":["Spain"],"villalcampo":["Spain"],"villalcazardesirga":["Spain"],"villalcon":["Spain"],"villaldama":["Mexico"],"villaldamanuevoleon":["Mexico"],"villaldemiro":["Spain"],"villalengua":["Spain"],"villalfonsina":["Italy"],"villalgordodeljucar":["Spain"],"villalgordodelmarquesado":["Spain"],"villalmanzo":["Spain"],"villalobarderioja":["Spain"],"villalobos":["Spain"],"villalobon":["Spain"],"villalonga":["Spain"],"villalonso":["Spain"],"villalpando":["Spain"],"villalpardo":["Spain"],"villalube":["Spain"],"villaluengadelasagra":["Spain"],"villaluengadelavega":["Spain"],"villaluengadelrosario":["Spain"],"villalvernia":["Italy"],"villalandecampos":["Spain"],"villalondecampos":["Spain"],"villamaina":["Italy"],"villamalea":["Spain"],"villamalur":["Spain"],"villamandos":["Spain"],"villamanrique":["Spain"],"villamanriquedelacondesa":["Spain"],"villamanriquedetajo":["Spain"],"villamanta":["Spain"],"villamantilla":["Spain"],"villamanin":["Spain"],"villamar":["Italy","Mexico"],"villamartin":["Spain"],"villamartindecampos":["Spain"],"villamartindedonsancho":["Spain"],"villamarzana":["Italy"],"villamassargia":["Italy"],"villamayor":["Spain"],"villamayordecalatrava":["Spain"],"villamayordecampos":["Spain"],"villamayordegallego":["Spain"],"villamayordelosmontes":["Spain"],"villamayordemonjardin":["Spain"],"villamayordesantiago":["Spain"],"villamayordetrevino":["Spain"],"villamanan":["Spain"],"villambistia":["Spain"],"villamediana":["Spain"],"villamedianadeiregua":["Spain"],"villamedianilla":["Spain"],"villamejil":["Spain"],"villamena":["Spain"],"villameriel":["Spain"],"villamesias":["Spain"],"villamiel":["Spain"],"villamieldelasierra":["Spain"],"villamieldetoledo":["Spain"],"villaminaya":["Spain"],"villamiroglio":["Italy"],"villammare":["Italy"],"villamol":["Spain"],"villamontes":["Bolivia"],"villamontandelavalduerna":["Spain"],"villamor":["Philippines"],"villamordelosescuderos":["Spain"],"villamoratieldelasmatas":["Spain"],"villamoronta":["Spain"],"villamuelas":["Spain"],"villamueradelacueza":["Spain"],"villamurieldecampos":["Spain"],"villamurieldecerrato":["Spain"],"villandro":["Italy"],"villandrovillanders":["Italy"],"villandry":["France"],"villangomez":["Spain"],"villanobeach":["United States"],"villanova":["Italy","Spain"],"villanovabiellese":["Italy"],"villanovacanavese":["Italy"],"villanovadalbenga":["Italy"],"villanovadardenghi":["Italy"],"villanovadasti":["Italy"],"villanovadelbattista":["Italy"],"villanovadelghebbocanton":["Italy"],"villanovadelsillaro":["Italy"],"villanovamarchesana":["Italy"],"villanovamondovi":["Italy"],"villanovamonferrato":["Italy"],"villanovamonteleone":["Italy"],"villanovasolaro":["Italy"],"villanovatruschedu":["Italy"],"villanovatulo":["Italy"],"villanovaforru":["Italy"],"villanovafranca":["Italy"],"villanterio":["Italy"],"villanubla":["Spain"],"villanuevadealcardete":["Spain"],"villanuevadealcoron":["Spain"],"villanuevadealgaidas":["Spain"],"villanuevadeargano":["Spain"],"villanuevadeargecilla":["Spain"],"villanuevadeazoague":["Spain"],"villanuevadebogas":["Spain"],"villanuevadecameros":["Spain"],"villanuevadecampean":["Spain"],"villanuevadecarazo":["Spain"],"villanuevadecastellon":["Spain"],"villanuevadecordoba":["Spain"],"villanuevadeduero":["Spain"],"villanuevadegormaz":["Spain"],"villanuevadeguadamejud":["Spain"],"villanuevadegumiel":["Spain"],"villanuevadegallego":["Spain"],"villanuevadegomez":["Spain"],"villanuevadehuerva":["Spain"],"villanuevadejiloca":["Spain"],"villanuevadelacanada":["Spain"],"villanuevadelaconcepcion":["Spain"],"villanuevadelacondesa":["Spain"],"villanuevadelafuente":["Spain"],"villanuevadelajara":["Spain"],"villanuevadelareina":["Spain"],"villanuevadelaserena":["Spain"],"villanuevadelasierra":["Spain"],"villanuevadelatorre":["Spain"],"villanuevadelavera":["Spain"],"villanuevadelascruces":["Spain"],"villanuevadelasmanzanas":["Spain"],"villanuevadelasperas":["Spain"],"villanuevadelastorres":["Spain"],"villanuevadeloscaballeros":["Spain"],"villanuevadeloscastillejos":["Spain"],"villanuevadelosinfantes":["Spain"],"villanuevadeoscos":["Spain"],"villanuevadeperales":["Spain"],"villanuevadesancarlos":["Spain"],"villanuevadesanjuan":["Spain"],"villanuevadesanmancio":["Spain"],"villanuevadesigena":["Spain"],"villanuevadetapia":["Spain"],"villanuevadeteba":["Spain"],"villanuevadeviver":["Spain"],"villanuevadeavila":["Spain"],"villanuevadelaceral":["Spain"],"villanuevadelariscal":["Spain"],"villanuevadelarzobispo":["Spain"],"villanuevadelcampillo":["Spain"],"villanuevadelcampo":["Spain"],"villanuevadelconde":["Spain"],"villanuevadelduque":["Spain"],"villanuevadelfresno":["Spain"],"villanuevadelpardillo":["Spain"],"villanuevadelrebollar":["Spain"],"villanuevadelrebollardelasierra":["Spain"],"villanuevadelrey":["Spain"],"villanuevadelrosario":["Spain"],"villanuevadelriosegura":["Spain"],"villanuevadelrioyminas":["Spain"],"villanuevadeltrabuco":["Spain"],"villanuevamesia":["Spain"],"villanuova":["Italy"],"villanuovasulclisi":["Italy"],"villanunodevaldavia":["Spain"],"villanazar":["Spain"],"villanua":["Spain"],"villaobispodeotero":["Spain"],"villaornateycastro":["Spain"],"villapalacios":["Spain"],"villaperuccio":["Italy"],"villapiana":["Italy"],"villapianalido":["Italy"],"villapinta":["Italy"],"villapinzon":["Colombia"],"villaprovedo":["Spain"],"villaputzu":["Italy"],"villaquejida":["Spain"],"villaquilambre":["Spain"],"villaquirandelapuebla":["Spain"],"villaquirandelosinfantes":["Spain"],"villardearganan":["Spain"],"villardearnedoel":["Spain"],"villardecanas":["Spain"],"villardeciervo":["Spain"],"villardecorneja":["Spain"],"villardedomingogarcia":["Spain"],"villardefallaves":["Spain"],"villardegallimazo":["Spain"],"villardelaencina":["Spain"],"villardelayegua":["Spain"],"villardelosnavarros":["Spain"],"villardeolalla":["Spain"],"villardeperalonso":["Spain"],"villardeplasencia":["Spain"],"villarderena":["Spain"],"villardesamaniego":["Spain"],"villardetorre":["Spain"],"villardelala":["Spain"],"villardelarzobispo":["Spain"],"villardelbuey":["Spain"],"villardelcampo":["Spain"],"villardelcobo":["Spain"],"villardelhumo":["Spain"],"villardelinfantado":["Spain"],"villardelolmo":["Spain"],"villardelpedroso":["Spain"],"villardelpozo":["Spain"],"villardelrey":["Spain"],"villardelrio":["Spain"],"villardelsalz":["Spain"],"villardora":["Italy"],"villarfocchiardo":["Italy"],"villarpellice":["Italy"],"villarperosa":["Italy"],"villarsancostanzo":["Italy"],"villaryvelasco":["Spain"],"villarsaintpancrace":["France"],"villaralbo":["Spain"],"villaralto":["Spain"],"villarbasse":["Italy"],"villarboit":["Italy"],"villarcayodemerindaddecastillalavieja":["Spain"],"villardbonnot":["France"],"villarddelans":["France"],"villardeciervos":["Spain"],"villardefrades":["Spain"],"villardieguadelaribera":["Spain"],"villardompardo":["Spain"],"villardondiego":["Spain"],"villareal":["Philippines"],"villareggia":["Italy"],"villarejo":["Spain"],"villarejodefuentes":["Spain"],"villarejodelapenuela":["Spain"],"villarejodemontalban":["Spain"],"villarejodesalvanes":["Spain"],"villarejodeorbigo":["Spain"],"villarejodelvalle":["Spain"],"villarejoperiesteban":["Spain"],"villaresdejadraque":["Spain"],"villaresdelareina":["Spain"],"villaresdesorialos":["Spain"],"villaresdeyeltes":["Spain"],"villaresdeorbigo":["Spain"],"villaresdelsaz":["Spain"],"villareslos":["Spain"],"villargondran":["France"],"villargordodelcabriel":["Spain"],"villaricca":["Italy"],"villariezo":["Spain"],"villarinodelosaires":["Spain"],"villarluengo":["Spain"],"villarmayor":["Spain"],"villarmenterodecampos":["Spain"],"villarmenterodeesgueva":["Spain"],"villarmuerto":["Spain"],"villaromagnano":["Italy"],"villarotta":["Italy"],"villarpando":["Dominican Republic"],"villarquemado":["Spain"],"villarrabe":["Spain"],"villarramiel":["Spain"],"villarrasa":["Spain"],"villarrealdehuerva":["Spain"],"villarrica":["Chile","Colombia","Paraguay"],"villarrobledo":["Spain"],"villarrodrigo":["Spain"],"villarroya":["Spain"],"villarroyadelasierra":["Spain"],"villarroyadelospinares":["Spain"],"villarroyadelcampo":["Spain"],"villarrubiadelosojos":["Spain"],"villarrubiadesantiago":["Spain"],"villarrubio":["Spain"],"villarrindecampos":["Spain"],"villars":["France"],"villarslesdombes":["France"],"villarssurglane":["Switzerland"],"villarssurollon":["Switzerland"],"villarta":["Spain"],"villartadelosmontes":["Spain"],"villartadesanjuan":["Spain"],"villartaquintana":["Spain"],"villas":["United States"],"villasdealcala":["Mexico"],"villasdeirapuato":["Mexico"],"villasdelahaciendafraccionamiento":["Mexico"],"villasdelalaguna":["Mexico"],"villasdelaloma":["Mexico"],"villasdelaventosa":["Spain"],"villasdelcampo":["Mexico"],"villasfundadoresfraccionamiento":["Mexico"],"villasabariego":["Spain"],"villasalto":["Italy"],"villasanademena":["Spain"],"villasanta":["Italy"],"villasarracino":["Spain"],"villasayas":["Spain"],"villasbuenas":["Spain"],"villasbuenasdegata":["Spain"],"villasdardo":["Spain"],"villasecadearciel":["Spain"],"villasecadehenares":["Spain"],"villasecadelasagra":["Spain"],"villasecadeuceda":["Spain"],"villasecodelosgamitos":["Spain"],"villasecodelosreyes":["Spain"],"villasecodelpan":["Spain"],"villaselan":["Spain"],"villasequilla":["Spain"],"villaseta":["Italy"],"villasexmir":["Spain"],"villasiladevaldavia":["Spain"],"villasimius":["Italy"],"villasis":["Philippines"],"villasmundo":["Italy"],"villasor":["Italy"],"villaspeciosa":["Italy"],"villasrubias":["Spain"],"villassio":["Italy"],"villastar":["Spain"],"villastellone":["Italy"],"villasurdeherreros":["Spain"],"villata":["Italy"],"villatobas":["Spain"],"villatora":["Italy"],"villatoro":["Spain"],"villatorres":["Spain"],"villatoya":["Spain"],"villatuelda":["Spain"],"villatuerta":["Spain"],"villaturde":["Spain"],"villaturiel":["Spain"],"villaudric":["France"],"villaumbrales":["Spain"],"villaurbana":["Italy"],"villavaatarrabia":["Spain"],"villavaliente":["Spain"],"villavallelonga":["Italy"],"villavaquerin":["Spain"],"villavelayo":["Spain"],"villavellid":["Spain"],"villavendimio":["Spain"],"villaverdedeguadalimar":["Spain"],"villaverdedeguarena":["Spain"],"villaverdedemedina":["Spain"],"villaverdedemontejo":["Spain"],"villaverdederioja":["Spain"],"villaverdedeiscar":["Spain"],"villaverdedelmonte":["Spain"],"villaverdedelrio":["Spain"],"villaverdeypasaconsol":["Spain"],"villaverdemogina":["Spain"],"villaverla":["Italy"],"villavezadevalverde":["Spain"],"villavezadelagua":["Spain"],"villavicencio":["Colombia"],"villavicenciodeloscaballeros":["Spain"],"villaviciosa":["Philippines","Spain"],"villaviciosadecordoba":["Spain"],"villaviciosadeodon":["Spain"],"villavieja":["Colombia","Spain"],"villaviejadeyeltes":["Spain"],"villaviejadellozoya":["Spain"],"villaviudas":["Spain"],"villawood":["Australia"],"villayernomorquillas":["Spain"],"villayon":["Spain"],"villaz":["France"],"villazsaintpierre":["Switzerland"],"villazala":["Spain"],"villazanzodevalderaduey":["Spain"],"villazopeque":["Spain"],"villazon":["Bolivia"],"villeplatte":["United States"],"villesursarre":["Italy"],"villedavray":["France"],"villelagrand":["France"],"villemarie":["Canada"],"villesousanjou":["France"],"villesouslaferte":["France"],"villebarou":["France"],"villebernier":["France"],"villeblevin":["France"],"villebois":["France"],"villebonsuryvette":["France"],"villebret":["France"],"villecresnes":["France"],"villecroze":["France"],"villedamorales":["Honduras"],"villedieulablouere":["France"],"villedieulespoeles":["France"],"villedieusurindre":["France"],"villedomer":["France"],"villefagnan":["France"],"villefontaine":["France"],"villefranche":["Italy"],"villefranchedalbigeois":["France"],"villefranchedelauragais":["France"],"villefranchederouergue":["France"],"villefranchedallier":["France"],"villefranchesurcher":["France"],"villefranchesurmer":["France"],"villefranchesursaone":["France"],"villefranque":["France"],"villegailhenc":["France"],"villegas":["Spain"],"villegouge":["France"],"villeguillo":["Spain"],"villejuif":["France"],"villejust":["France"],"villel":["Spain"],"villeldemesa":["Spain"],"villelaure":["France"],"villelonguedelasalanque":["France"],"villemandeur":["France"],"villemeuxsureure":["France"],"villemoirieu":["France"],"villemoissonsurorge":["France"],"villemolaque":["France"],"villemomble":["France"],"villemoustaussou":["France"],"villemursurtarn":["France"],"villena":["Spain"],"villenauxelagrande":["France"],"villenavedornon":["France"],"villenbach":["Germany"],"villeneuve":["France","Italy","Switzerland"],"villeneuvedascq":["France"],"villeneuvedeberg":["France"],"villeneuvedelaraho":["France"],"villeneuvedemarsan":["France"],"villeneuvederiviere":["France"],"villeneuvedolmes":["France"],"villeneuvelacomptal":["France"],"villeneuvelagarenne":["France"],"villeneuvelaguyard":["France"],"villeneuvelariviere":["France"],"villeneuvelecomte":["France"],"villeneuveleroi":["France"],"villeneuvelessablons":["France"],"villeneuveloubet":["France"],"villeneuvelesavignon":["France"],"villeneuvelesbouloc":["France"],"villeneuvelesbeziers":["France"],"villeneuvelesmaguelone":["France"],"villeneuvesaintgeorges":["France"],"villeneuvesaintgermain":["France"],"villeneuvesurbellot":["France"],"villeneuvesurlot":["France"],"villeneuvesuryonne":["France"],"villeneuvetolosane":["France"],"villennessurseine":["France"],"villenouvelle":["France"],"villenoy":["France"],"villeparisis":["France"],"villepinte":["France"],"villepreux":["France"],"villerest":["France"],"villereversure":["France"],"villersbocage":["France"],"villersbretonneux":["France"],"villerscotterets":["France"],"villersencauchies":["France"],"villerslamontagne":["France"],"villerslaville":["Belgium"],"villerslebouillet":["Belgium"],"villerslelac":["France"],"villerslesnancy":["France"],"villersoutreaux":["France"],"villerspol":["France"],"villerssaintpaul":["France"],"villerssemeuse":["France"],"villerssoussaintleu":["France"],"villerssurcoudun":["France"],"villerssurmer":["France"],"villersecalles":["France"],"villersexel":["France"],"villerupt":["France"],"villereal":["France"],"villeriasdecampos":["Spain"],"villessurauzon":["France"],"villesse":["Italy"],"villeta":["Colombia"],"villetaneuse":["France"],"villetelle":["France"],"villettabarrea":["Italy"],"villette":["Italy"],"villettedevienne":["France"],"villeurbanne":["France"],"villevaude":["France"],"villeveyrac":["France"],"villevieille":["France"],"villevocance":["France"],"villeveque":["France"],"villeysaintetienne":["France"],"villiers":["South Africa"],"villiersenlieu":["France"],"villiersenplaine":["France"],"villierslebel":["France"],"villierslebacle":["France"],"villierslemorhier":["France"],"villierssaintfrederic":["France"],"villierssaintgeorges":["France"],"villierssurloir":["France"],"villierssurmarne":["France"],"villierssurmorin":["France"],"villierssurorge":["France"],"villigen":["Switzerland"],"villimpenta":["Italy"],"villingenschwenningen":["Germany"],"villingendorf":["Germany"],"villisca":["United States"],"villiemorgon":["France"],"villmar":["Germany"],"villmergen":["Switzerland"],"villnachern":["Switzerland"],"villodre":["Spain"],"villodrigo":["Spain"],"villoldo":["Spain"],"villongo":["Italy"],"villores":["Spain"],"villoruebo":["Spain"],"villoruela":["Spain"],"villoria":["Spain"],"villosladadecameros":["Spain"],"villotadelparamo":["Spain"],"villotta":["Italy"],"villovieco":["Spain"],"villupuram":["India"],"villandetordesillas":["Spain"],"villany":["Hungary"],"villardiga":["Spain"],"ville":["France"],"vilminore":["Italy"],"vilminorediscalve":["Italy"],"vilnianskraion":["Ukraine"],"vilnius":["Lithuania"],"vilniusdistrictmunicipality":["Lithuania"],"vilobidelpenedes":["Spain"],"vilobidonyar":["Spain"],"viloco":["Bolivia"],"vilonia":["United States"],"vilopriu":["Spain"],"viloria":["Spain"],"viloriaderioja":["Spain"],"vilosellel":["Spain"],"vilovatovo":["Russia"],"vilovo":["Serbia"],"vilppula":["Finland"],"vils":["Austria"],"vilsbiburg":["Germany"],"vilseck":["Germany"],"vilsheim":["Germany"],"vilshofen":["Germany"],"viluenala":["Spain"],"vilvestre":["Spain"],"vilviestredelpinar":["Spain"],"vilvoorde":["Belgium"],"vilya":["Russia"],"vilyeyka":["Belarus"],"vilyeyskirayon":["Belarus"],"vilyuchinsk":["Russia"],"vilyuysk":["Russia"],"vilyuyskiyrayon":["Russia"],"vilyuyskydistrict":["Russia"],"vilemov":["Czech Republic"],"vilne":["Ukraine"],"vimamare":["Romania"],"vimamica":["Romania"],"vimbodiipoblet":["Spain"],"vimeiro":["Portugal"],"vimercate":["Italy"],"vimianzo":["Spain"],"vimines":["France"],"vimioso":["Portugal"],"vimmerby":["Sweden"],"vimodrone":["Italy"],"vimory":["France"],"vimoutiers":["France"],"vimpeli":["Finland"],"vimperk":["Czech Republic"],"vimy":["France"],"vina":["Cameroon"],"vinaceite":["Spain"],"vinadio":["Italy"],"vinaixa":["Spain"],"vinalesa":["Spain"],"vinalhaven":["United States"],"vinaros":["Spain"],"vinassan":["France"],"vinay":["France"],"vinarice":["Czech Republic"],"vincennes":["France","United States"],"vincent":["Australia","United States"],"vincentia":["Australia"],"vincentown":["United States"],"vinces":["Ecuador"],"vincey":["France"],"vinchhiya":["India"],"vinchia":["India"],"vinchiaturo":["Italy"],"vinchina":["Argentina"],"vinchio":["Italy"],"vinchur":["India"],"vinci":["Italy"],"vinco":["United States"],"vindafjord":["Norway"],"vindeby":["Denmark"],"vindel":["Spain"],"vindeln":["Sweden"],"vinderei":["Romania"],"vinderup":["Denmark"],"vindhyachal":["India"],"vindinge":["Denmark"],"vinegrove":["United States"],"vinehill":["United States"],"vinebre":["Spain"],"vineland":["Canada","United States"],"vinerea":["Romania"],"vineuil":["France"],"vineuilsaintfirmin":["France"],"vineyard":["Australia","United States"],"vineyardhaven":["United States"],"vineyardtown":["Jamaica"],"vineyards":["United States"],"vinez":["Croatia"],"vinga":["Romania"],"vingtcinq":["Mauritius"],"vingaker":["Sweden"],"vinh":["Vietnam"],"vinhais":["Portugal"],"vinhedo":["Brazil"],"vinho":["Portugal"],"vinica":["Croatia","Macedonia"],"viniegradeabajo":["Spain"],"viniegradearriba":["Spain"],"vinings":["United States"],"vinita":["United States"],"vinitapark":["United States"],"vinicnesumice":["Czech Republic"],"vinje":["Norway"],"vinkebrug":["Netherlands"],"vinkeveen":["Netherlands"],"vinkovci":["Croatia"],"vinneuf":["France"],"vinni":["Estonia"],"vinnivald":["Estonia"],"vinninga":["Sweden"],"vinningen":["Germany"],"vinnitskiyrayon":["Ukraine"],"vinnitskoye":["Ukraine"],"vinnitsy":["Russia"],"vinnytsia":["Ukraine"],"vinne":["Slovakia"],"vinodolskaopcina":["Croatia"],"vinogradnoye":["Ukraine"],"vinogradnyy":["Russia"],"vinogradovo":["Russia","Ukraine"],"vinonsurverdon":["France"],"vinosady":["Slovakia"],"vinovo":["Italy"],"vinsady":["Russia"],"vinslov":["Sweden"],"vinsobres":["France"],"vinstra":["Norway"],"vintar":["Philippines"],"vintere":["Romania"],"vintileanca":["Romania"],"vintileasca":["Romania"],"vintilavoda":["Romania"],"vinton":["United States"],"vintoncounty":["United States"],"vintrosa":["Sweden"],"vintirov":["Czech Republic"],"vinuesa":["Spain"],"vinukonda":["India"],"vinyolsielsarcs":["Spain"],"vinzaglio":["Italy"],"vinzili":["Russia"],"vinzons":["Philippines"],"vinca":["France"],"vintudejos":["Romania"],"viola":["Italy","United States"],"violaines":["France"],"violay":["France"],"violet":["United States"],"violes":["France"],"violicharaki":["Greece"],"vion":["France"],"vione":["Italy"],"vionnaz":["Switzerland"],"viota":["Colombia"],"vipava":["Slovenia"],"viperesti":["Romania"],"vipiteno":["Italy"],"vipperod":["Denmark"],"viqueque":["East Timor"],"vir":["Croatia","Slovenia"],"virac":["Philippines"],"viracacha":["Colombia"],"viradouro":["Brazil"],"viraganur":["India"],"viramgam":["India"],"viransehir":["Turkey"],"virar":["India"],"virarajendrapet":["India"],"virazeil":["France"],"virbalis":["Lithuania"],"virden":["Canada","United States"],"vire":["France"],"vireuxmolhain":["France"],"vireuxwallerand":["France"],"vireylegrand":["France"],"virgemdalapa":["Brazil"],"virgen":["Austria"],"virgil":["Canada"],"virginia":["Brazil"],"virginiabeach":["United States"],"virginiacity":["United States"],"virginiagardens":["United States"],"virginiawater":["United Kingdom"],"virginias":["Mexico"],"virginopolis":["Brazil"],"virgolandia":["Brazil"],"viriat":["France"],"viriato":["Philippines"],"virieu":["France"],"virieulegrand":["France"],"viriville":["France"],"virje":["Croatia"],"virklund":["Denmark"],"virlepiemonte":["Italy"],"virlya":["Ukraine"],"virmond":["Brazil"],"viroflay":["France"],"virojoki":["Finland"],"viroqua":["United States"],"virovitica":["Croatia"],"virpur":["India"],"virrat":["Finland"],"virserum":["Sweden"],"virtasalmi":["Finland"],"virton":["Belgium"],"viru":["Peru"],"virunigulavald":["Estonia"],"virudhunagar":["India"],"viry":["France"],"virychatillon":["France"],"virynoureuil":["France"],"viros":["Greece"],"vis":["Croatia"],"visaginas":["Lithuania"],"visakhapatnam":["India"],"visalia":["United States"],"visan":["France"],"visano":["Italy"],"visavadar":["India"],"visbek":["Germany"],"visby":["Sweden"],"vische":["Italy"],"visciano":["Italy"],"visco":["Italy"],"viscondedoriobranco":["Brazil"],"viscri":["Romania"],"visegrad":["Bosnia and Herzegovina"],"viseu":["Brazil","Portugal"],"vishennoye":["Ukraine"],"vishnyakovskiyedachi":["Russia"],"vishnyeva":["Belarus"],"vishnyovka":["Ukraine"],"vishnevogorsk":["Russia"],"vishow":["Belarus"],"visiedo":["Spain"],"visim":["Russia"],"visitacionvalley":["United States"],"viskafors":["Sweden"],"vislanda":["Sweden"],"visnagar":["India"],"visodesanjuanel":["Spain"],"visodelalcorel":["Spain"],"visodelmarques":["Spain"],"visoel":["Spain"],"visoko":["Bosnia and Herzegovina"],"visone":["Italy"],"visp":["Switzerland"],"vispdistrict":["Switzerland"],"visperterminen":["Switzerland"],"visselhovede":["Germany"],"vissenbjerg":["Denmark"],"visso":["Italy"],"vista":["United States"],"vistaalegre":["Argentina","Brazil","Panama","Philippines"],"vistaalegredoalto":["Brazil"],"vistaalegredoprata":["Brazil"],"vistacenter":["United States"],"vistagaucha":["Brazil"],"vistahermosa":["Colombia"],"vistahermosacuasinada":["Mexico"],"vistahermosadenegrete":["Mexico"],"vistasantarosa":["United States"],"vistaserrana":["Brazil"],"vistabella":["Spain"],"vistabelladelmaestrazgo":["Spain"],"vistarino":["Italy"],"vistasdelmagueyfraccionamiento":["Mexico"],"vistha":["Mexico"],"vistino":["Russia"],"vistrorio":["Italy"],"vise":["Belgium"],"vita":["Italy","Spain"],"vitamaharashtra":["India"],"vitacura":["Chile"],"vitali":["Philippines"],"vitanje":["Slovenia"],"vite":["India"],"vitebsk":["Belarus"],"viterbo":["Colombia","Italy"],"vitez":["Bosnia and Herzegovina"],"viticuso":["Italy"],"vitigliano":["Italy"],"vitigudino":["Spain"],"vitim":["Russia"],"vitina":["Bosnia and Herzegovina"],"vitinia":["Italy"],"vitis":["Austria"],"vito":["Mexico","Philippines"],"vitomarci":["Slovenia"],"vitomiresti":["Romania"],"vitormeireles":["Brazil"],"vitorchiano":["Italy"],"vitoriagasteiz":["Spain"],"vitorino":["Brazil"],"vitorinofreire":["Brazil"],"vitrolles":["France"],"vitryauxloges":["France"],"vitryenartois":["France"],"vitrylefrancois":["France"],"vitrysurorne":["France"],"vitrysurseine":["France"],"vitre":["France"],"vitteaux":["France"],"vittel":["France"],"vittoria":["Italy"],"vittorioveneto":["Italy"],"vittoriosa":["Malta"],"vittorito":["Italy"],"vittsjo":["Sweden"],"vittuone":["Italy"],"vitulano":["Italy"],"vitulazio":["Italy"],"vityazevo":["Russia"],"vitznau":["Switzerland"],"vitoria":["Brazil"],"vitoriabrasil":["Brazil"],"vitoriadaconquista":["Brazil"],"vitoriadasmissoes":["Brazil"],"vitoriadesantoantao":["Brazil"],"vitoriadojari":["Brazil"],"vitoriadomearim":["Brazil"],"vitoriadoxingu":["Brazil"],"vitanesti":["Romania"],"viuzensallaz":["France"],"viuzlachiesaz":["France"],"vivacardenas":["Mexico"],"vivamexico":["Mexico"],"vivaro":["Italy"],"vivaroromano":["Italy"],"viveash":["Australia"],"viveiro":["Spain"],"viveldelriomartin":["Spain"],"viver":["Spain"],"viveriserrateix":["Spain"],"viverone":["Italy"],"viveros":["Spain"],"vivian":["United States"],"vivieraucourt":["France"],"viviers":["France"],"viviersdulac":["France"],"vivierslesmontagnes":["France"],"viviez":["France"],"vivonne":["France"],"vivy":["France"],"vix":["France"],"viytivka":["Ukraine"],"vizalsanpablo":["Philippines"],"vizalsantonino":["Philippines"],"vizanteamanastireasca":["Romania"],"vizarron":["Mexico"],"vizcachane":["Peru"],"vizcainos":["Spain"],"vize":["Turkey"],"vizela":["Portugal"],"vizianagaram":["India"],"vizianagaramdistrict":["India"],"vizille":["France"],"vizinga":["Russia"],"viziru":["Romania"],"vizmanos":["Spain"],"vizovice":["Czech Republic"],"vizuresti":["Romania"],"vizzini":["Italy"],"vizzolaticino":["Italy"],"vizzolopredabissi":["Italy"],"vicosa":["Brazil"],"vicosadoceara":["Brazil"],"vinadelmar":["Chile"],"vinales":["Cuba"],"vinas":["Spain"],"vinasdelsol":["Mexico"],"vinegrademorana":["Spain"],"vinuela":["Spain"],"vinuelas":["Spain"],"viol":["Germany"],"viu":["Italy"],"vicdistrict":["Slovenia"],"vilaka":["Latvia"],"vilani":["Latvia"],"visani":["Romania"],"viseudejos":["Romania"],"viseudesus":["Romania"],"visina":["Romania"],"visinesti":["Romania"],"visniovca":["Moldova"],"viskovci":["Croatia"],"viskovo":["Croatia"],"visnjanvisignano":["Croatia"],"visnjevac":["Croatia"],"visnjicevo":["Serbia"],"visnova":["Czech Republic"],"visnove":["Czech Republic"],"vizinadavisinada":["Croatia"],"viseudemijloc":["Romania"],"visinanoua":["Romania"],"visinelu":["Romania"],"visteadejos":["Romania"],"viettri":["Vietnam"],"vicar":["Spain"],"victorrosales":["Mexico"],"vidolala":["Spain"],"vilia":["Greece"],"villora":["Spain"],"vitkov":["Czech Republic"],"viznar":["Spain"],"vinhlong":["Vietnam"],"vinhthanh":["Vietnam"],"vinhyen":["Vietnam"],"vithanh":["Vietnam"]}