{"vrachnaiika":["Greece"],"vracov":["Czech Republic"],"vradiyivka":["Ukraine"],"vrakhati":["Greece"],"vranestica":["Macedonia"],"vrangel":["Russia"],"vrani":["Romania"],"vranic":["Serbia"],"vranje":["Serbia"],"vranjic":["Croatia"],"vranovnadtoplou":["Slovakia"],"vranovice":["Czech Republic"],"vransko":["Slovenia"],"vrana":["Greece"],"vranenadvltavou":["Czech Republic"],"vrapciste":["Macedonia"],"vrata":["Romania"],"vratimov":["Czech Republic"],"vratisinec":["Croatia"],"vratnica":["Macedonia"],"vratsa":["Bulgaria"],"vrbanja":["Croatia"],"vrbas":["Serbia"],"vrbice":["Czech Republic"],"vrbnik":["Croatia"],"vrbnopodpradedem":["Czech Republic"],"vrbov":["Slovakia"],"vrbovec":["Croatia","Czech Republic"],"vrbovsko":["Croatia"],"vrbove":["Slovakia"],"vrbatky":["Czech Republic"],"vrchlabi":["Czech Republic"],"vrdnik":["Serbia"],"vrdy":["Czech Republic"],"vred":["France"],"vrede":["South Africa"],"vredefort":["South Africa"],"vreden":["Germany"],"vredenburg":["Netherlands","South Africa"],"vredendal":["South Africa"],"vreedenhoop":["Guyana"],"vrees":["Germany"],"vreeswijk":["Netherlands"],"vreewijk":["Netherlands"],"vrgorac":["Croatia"],"vrhnika":["Slovenia"],"vriddhachalam":["India"],"vrieheide":["Netherlands"],"vries":["Netherlands"],"vriezenveen":["Netherlands"],"vrigneauxbois":["France"],"vrigstad":["Sweden"],"vrilissia":["Greece"],"vrindavan":["India"],"vrlika":["Croatia"],"vrnjackabanja":["Serbia"],"vrnograc":["Bosnia and Herzegovina"],"vrontou":["Greece"],"vroomshoop":["Netherlands"],"vroutek":["Czech Republic"],"vrpolje":["Croatia"],"vrsar":["Croatia"],"vrsarorsera":["Croatia"],"vrsi":["Croatia"],"vrtojba":["Slovenia"],"vrutok":["Macedonia"],"vryburg":["South Africa"],"vryheid":["South Africa"],"vrable":["Slovakia"],"vrancioaia":["Romania"],"vra":["Denmark"],"vrutky":["Slovakia"],"vryses":["Greece"],"vranesti":["Romania"],"vrsac":["Serbia"],"vresina":["Czech Republic"]}